IQS_algorithm/IQS.py
IQS_algorithm/__init__.py
IQS_algorithm/IQS_utils/__init__.py
IQS_algorithm/IQS_utils/funcIQS.py
IQS_algorithm/IQS_utils/RelevantFiles/__init__.py
IQS_algorithm/IQS_utils/RelevantFiles/glove-wiki-gigaword-50.txt
tests/__init__.py
IQS_algorithm-1.0.0.dist-info/LICENSE
IQS_algorithm-1.0.0.dist-info/METADATA
IQS_algorithm-1.0.0.dist-info/WHEEL
IQS_algorithm-1.0.0.dist-info/top_level.txt
IQS_algorithm-1.0.0.dist-info/RECORD
